MANIFEST.in
README.rst
setup.cfg
setup.py
emit/__init__.py
emit/graphviz.py
emit/messages.py
emit/multilang.py
emit.egg-info/PKG-INFO
emit.egg-info/SOURCES.txt
emit.egg-info/dependency_links.txt
emit.egg-info/requires.txt
emit.egg-info/top_level.txt
emit.egg-info/zip-safe
emit/bin/emit_digraph
emit/router/__init__.py
emit/router/celery.py
emit/router/core.py
emit/router/rq.py
tests/__init__.py
tests/message_tests.py
tests/multilang_tests.py
tests/router_celery_tests.py
tests/router_core_tests.py
tests/router_rq_tests.py
tests/utils.py